<entries>
<entry name="Health">Sağlık</entry>
<entry name="Level11">2-yıldızlı Kaptan</entry>
<entry name="Level12">3-yıldızlı Kaptan</entry>
<entry name="Level13">Majör</entry>
<entry name="Level14">1-yıldızlı Binbaşı</entry>
<entry name="Level15">2-yıldızlı Binbaşı</entry>
<entry name="Level16">3-yıldızlı Binbaşı</entry>
<entry name="About">Yaklaşık</entry>
<entry name="Gravity">Yerçekimi</entry>
<entry name="Task">Görev</entry>
<entry name="Level1">Çavuş</entry>
<entry name="Level2">1-yıldızlı Çavuş</entry>
<entry name="quitTitle">Oyundan çıkmak?</entry>
<entry name="GameSettings">Oyun ayarları</entry>
<entry name="playCnt">Oyunlar</entry>
<entry name="Level6">1-yıldızlı Teğmen</entry>
<entry name="Level7">2-yıldızlı Teğmen</entry>
<entry name="Turns">Dönüşler</entry>
<entry name="Level9">Kaptan</entry>
<entry name="Award">Ödül</entry>
<entry name="Level18">1-yıldızlı Albay</entry>
<entry name="Levelnote">Eleme</entry>
<entry name="try">denemek</entry>
<entry name="Language">Lisan</entry>
<entry name="Level20">3-yıldızlı Albay</entry>
<entry name="Vibration">Titreşim</entry>
<entry name="Level4">3-yıldızlı Çavuş</entry>
<entry name="Level5">Teğmen</entry>
<entry name="Level24">3-yıldızlı Genel</entry>
<entry name="CurScore">Güncel puanı</entry>
<entry name="Daily">Günlük</entry>
<entry name="cancel">Iptal etmek</entry>
<entry name="coin">Madeni para</entry>
<entry name="pass">İlk boyunca</entry>
<entry name="pause">Pause</entry>
<entry name="Purchase">Satın</entry>
<entry name="Level22">1-yıldızlı Genel</entry>
<entry name="Level23">2-yıldızlı Genel</entry>
<entry name="goldShortage">Altın sıkıntısı!</entry>
<entry name="buyProps">Sahne Satın</entry>
<entry name="Touch">Dokunma</entry>
<entry name="BestScore">İyi Skor</entry>
<entry name="actCnt">Toplu davranış</entry>
<entry name="Resume">Devam</entry>
<entry name="Level10">1-yıldızlı Captain</entry>
<entry name="ok">Onaylamak</entry>
<entry name="spaceship">Değişim Uzay Gemisi</entry>
<entry name="GameHelp">Oyun Yardım</entry>
<entry name="menu">Menü</entry>
<entry name="Speed">Hız</entry>
<entry name="Level17">Albay</entry>
<entry name="quitContent">Şimdi oyundan çıkmak istediğinizi onaylayın?</entry>
<entry name="propsName">Isim</entry>
<entry name="Force">Kuvvet</entry>
<entry name="TurnOff">Kapamak</entry>
<entry name="have">Var</entry>
<entry name="Location">Konum</entry>
<entry name="Second">İkinci</entry>
<entry name="Quit">Çıkmak</entry>
<entry name="Music">Müzik</entry>
<entry name="propsCnt">Destekler</entry>
<entry name="Battle">Savaş</entry>
<entry name="Level19">2-yıldızlı Albay</entry>
<entry name="restart">tekrar başlat</entry>
<entry name="continue">Devam</entry>
<entry name="Open">Açık</entry>
<entry name="totalPrice">Fiyat</entry>
<entry name="Level21">General</entry>
<entry name="Level3">2-yıldızlı Çavuş</entry>
<entry name="Operation">Operasyon</entry>
<entry name="consumption">Toplu tüketim</entry>
<entry name="Level8">3-yıldızlı Teğmen</entry>
<entry name="Sound">Ses</entry>
<entry name="quantity">Nicelik</entry>
<entry name="next">Sonraki</entry>
<entry name="Play">Oyun</entry>
<entry name="Rate">Oranı</entry>
<entry name="Share">Paylaş</entry>
<entry name="Setting">Ayarı</entry>
<entry name="currentscore">Geçerli puanı</entry>
<entry name="bestscore">En iyi müzik</entry>
<entry name="yourrank">Sizin seviyeniz</entry>
<entry name="None">Hiçbiri</entry>
<entry name="Help">Yardım</entry>
<entry name="missionday">Mission Day</entry>
</entries>
